{
  "id": "5fa8c0f400dbfa002456cffd",
  "title": "LINE Clova(ハードウェア)",
  "created": 1604894967,
  "updated": 1666840397,
  "lines": [
    {
      "id": "5fa8c0f400dbfa002456cffd",
      "text": "LINE Clova(ハードウェア)",
      "userId": "6055950b87138f0022246f59",
      "created": 1604894967,
      "updated": 1616418249
    },
    {
      "id": "5fa8c0f6d438750000f71013",
      "text": "",
      "userId": "5fa258bdb102120024d43875",
      "created": 1604894967,
      "updated": 1604894967
    },
    {
      "id": "5fa8c0f7d438750000f71014",
      "text": "初代の予約価格は10000円だった",
      "userId": "5fa258bdb102120024d43875",
      "created": 1604894967,
      "updated": 1604894977
    },
    {
      "id": "5fa8c100d438750000f71016",
      "text": "ソフトウェアに調整に時間がかかり､出荷が遅れていた",
      "userId": "5fa258bdb102120024d43875",
      "created": 1604894977,
      "updated": 1604894993
    },
    {
      "id": "5fa8c15cd438750000f7101e",
      "text": "",
      "userId": "5fa258bdb102120024d43875",
      "created": 1604895069,
      "updated": 1604895069
    },
    {
      "id": "5fa8c15cd438750000f7101f",
      "text": "パッケージ",
      "userId": "5fa258bdb102120024d43875",
      "created": 1604895069,
      "updated": 1604895072
    },
    {
      "id": "5fa8c15fd438750000f71020",
      "text": "　ケーキのラッピングのようだった",
      "userId": "5fa258bdb102120024d43875",
      "created": 1604895072,
      "updated": 1604895080
    },
    {
      "id": "5fa8c167d438750000f71022",
      "text": "　OOBEが[- 素晴らしい]のに､未熟なアシスタントでUXが良くないという対比が話題だった",
      "userId": "5fa258bdb102120024d43875",
      "created": 1604895080,
      "updated": 1604895161
    },
    {
      "id": "5fa8c110d438750000f71017",
      "text": "",
      "userId": "5fa258bdb102120024d43875",
      "created": 1604894993,
      "updated": 1604894993
    },
    {
      "id": "5fa8c111d438750000f71018",
      "text": "単体で[IRリモコン]として使える",
      "userId": "60508ed36a7abc00235e90c0",
      "created": 1604894994,
      "updated": 1666840397
    },
    {
      "id": "5fa8c18cd438750000f71023",
      "text": " ｢Clova,テレビを消して｣という[CM]でテレビの電源が消えてしまう事例があった",
      "userId": "6055950b87138f0022246f59",
      "created": 1604895117,
      "updated": 1616418221
    },
    {
      "id": "5fbbaf2d1280f000000bf073",
      "text": " 草",
      "userId": "5ef2bdebb60650001e1280f0",
      "created": 1606135598,
      "updated": 1606135599
    },
    {
      "id": "5fa8c1add438750000f71024",
      "text": "",
      "userId": "5fa258bdb102120024d43875",
      "created": 1604895150,
      "updated": 1604895151
    },
    {
      "id": "5fa8c11bd438750000f71019",
      "text": "[LINE]アカウントの連携が必須",
      "userId": "6055950b87138f0022246f59",
      "created": 1604895004,
      "updated": 1616418217
    },
    {
      "id": "5fa8c12ad438750000f7101a",
      "text": "",
      "userId": "5fa258bdb102120024d43875",
      "created": 1604895018,
      "updated": 1604895018
    },
    {
      "id": "5fa8c12ad438750000f7101b",
      "text": "[Bluetoothスピーカー]としても使える",
      "userId": "60508ed36a7abc00235e90c0",
      "created": 1604895018,
      "updated": 1666840390
    },
    {
      "id": "5fa8c0f8d438750000f71015",
      "text": "",
      "userId": "5fa258bdb102120024d43875",
      "created": 1604894969,
      "updated": 1606135149
    },
    {
      "id": "5fbbad6bd438750000ce6df9",
      "text": "[https://gyazo.com/d71d5b19f68542c1460cbfcb8377c580]",
      "userId": "5fa258bdb102120024d43875",
      "created": 1606135148,
      "updated": 1606135262
    },
    {
      "id": "5fbbadddd438750000ce6dfa",
      "text": "",
      "userId": "5fa258bdb102120024d43875",
      "created": 1606135262,
      "updated": 1606135262
    }
  ]
}