{
  "id": "603b92bf5dc4b600230e2b62",
  "title": "エコーチェンバー現象",
  "created": 1614516930,
  "updated": 1664603791,
  "lines": [
    {
      "id": "603b92bf5dc4b600230e2b62",
      "text": "エコーチェンバー現象",
      "userId": "5b5e7121417cf700145b98c2",
      "created": 1614516930,
      "updated": 1614516930
    },
    {
      "id": "603b92c15b98c20000745058",
      "text": ">《[echo chamber]は[反響室]の意》[SNS]において、[価値観]の似た者同士で交流し、[共感]し合うことにより、特定の[意見]や思想が増幅されて[影響力]をもつ現象。攻撃的な意見や[誤情報]などが広まる一因ともみられている。",
      "userId": "62a91a7a083437001de60035",
      "created": 1614516930,
      "updated": 1664603736
    },
    {
      "id": "603b92e85b98c2000074505a",
      "text": "[https://kotobank.jp/word/%E3%82%A8%E3%82%B3%E3%83%BC%E3%83%81%E3%82%A7%E3%83%B3%E3%83%90%E3%83%BC%E7%8F%BE%E8%B1%A1-1812458 エコーチェンバー現象とは - コトバンク]",
      "userId": "5b5e7121417cf700145b98c2",
      "created": 1614516968,
      "updated": 1614516969
    },
    {
      "id": "603b92e95b98c2000074505b",
      "text": "",
      "userId": "5b5e7121417cf700145b98c2",
      "created": 1614516969,
      "updated": 1614516969
    },
    {
      "id": "6337d68ce600350000605acd",
      "text": ">エコーチェンバー現象（エコーチェンバーげんしょう/[反響室現象]、英: echo chamber）とは、[電子掲示板]やSNSの、自分と似た意見や思想を持った人々が集まる場にて、自分の意見や思想が肯定されることで、それらが正解であるかのごとく勘違いする、又は価値観の似た者同士で交流・共感し合うことにより、特定の意見や思想が増幅する現象。閉鎖空間で似た者同士で意見をSNSで発信すると自分と似た意見が返ってきて増幅していく状況を、閉じた小部屋で音が反響する物理現象から例えたものである。",
      "userId": "62a91a7a083437001de60035",
      "created": 1664603788,
      "updated": 1664603791
    },
    {
      "id": "603b92ee5b98c2000074505c",
      "text": "[https://ja.wikipedia.org/wiki/%E3%82%A8%E3%82%B3%E3%83%BC%E3%83%81%E3%82%A7%E3%83%B3%E3%83%90%E3%83%BC%E7%8F%BE%E8%B1%A1 エコーチェンバー現象 - Wikipedia]",
      "userId": "5b5e7121417cf700145b98c2",
      "created": 1614516975,
      "updated": 1614517011
    },
    {
      "id": "60be9fba8ee92a0000f0a990",
      "text": "",
      "userId": "566fa156776c9b11008ee92a",
      "created": 1623105467,
      "updated": 1623105467
    },
    {
      "id": "60be9fba8ee92a0000f0a991",
      "text": "#フィルターバブル",
      "userId": "566fa156776c9b11008ee92a",
      "created": 1623105467,
      "updated": 1638414970
    },
    {
      "id": "603b93125b98c2000074505d",
      "text": "#エコーチェンバー",
      "userId": "5ef2bdebb60650001e1280f0",
      "created": 1614517011,
      "updated": 1646779401
    },
    {
      "id": "6227dc081280f00000b433ac",
      "text": "[echo chamber現象]",
      "userId": "5ef2bdebb60650001e1280f0",
      "created": 1646779399,
      "updated": 1646779416
    },
    {
      "id": "6227dc161280f00000b433ad",
      "text": "",
      "userId": "5ef2bdebb60650001e1280f0",
      "created": 1646779414,
      "updated": 1646779414
    }
  ]
}