{
  "id": "6082bb29b0441c002324d565",
  "title": "天空の城ラピュタ",
  "created": 1619180332,
  "updated": 1690085065,
  "lines": [
    {
      "id": "6082bb29b0441c002324d565",
      "text": "天空の城ラピュタ",
      "userId": "6055950b87138f0022246f59",
      "created": 1619180332,
      "updated": 1619180332
    },
    {
      "id": "64bc85515e90c00000580601",
      "text": "[https://gyazo.com/1ddf92e21c27fcf60c66174fa6e2b83d]",
      "userId": "60508ed36a7abc00235e90c0",
      "created": 1690076496,
      "updated": 1690076498
    },
    {
      "id": "64bc85585e90c00000580603",
      "text": " [https://www.ghibli.jp/works/laputa/#frame&gid=1&pid=36 天空の城ラピュタ - スタジオジブリ｜STUDIO GHIBLI]",
      "userId": "60508ed36a7abc00235e90c0",
      "created": 1690076503,
      "updated": 1690076506
    },
    {
      "id": "64bc855b5e90c00000580604",
      "text": "",
      "userId": "60508ed36a7abc00235e90c0",
      "created": 1690076506,
      "updated": 1690076507
    },
    {
      "id": "64bc85535e90c00000580602",
      "text": "",
      "userId": "60508ed36a7abc00235e90c0",
      "created": 1690076498,
      "updated": 1690076498
    },
    {
      "id": "6082bb2c246f590000edee01",
      "text": "プロットは小学生時代に温めていたものらしい",
      "userId": "6055950b87138f0022246f59",
      "created": 1619180332,
      "updated": 1619180344
    },
    {
      "id": "6082bb2f246f590000edee02",
      "text": "　「パズーの物語」",
      "userId": "6055950b87138f0022246f59",
      "created": 1619180336,
      "updated": 1619180354
    },
    {
      "id": "6082bb3c246f590000edee03",
      "text": "",
      "userId": "6055950b87138f0022246f59",
      "created": 1619180349,
      "updated": 1619180349
    },
    {
      "id": "6082cf0855cbd30000af6bf5",
      "text": "[未来少年コナン]と[ふしぎの海のナディア]もみよう",
      "userId": "5ae7fecf7766b7001455cbd3",
      "created": 1619185417,
      "updated": 1619185515
    },
    {
      "id": "6082cf0d55cbd30000af6bf6",
      "text": "　ナディアはよく考えたら[シン・コナン]じゃん",
      "userId": "5ae7fecf7766b7001455cbd3",
      "created": 1619185422,
      "updated": 1619185699
    },
    {
      "id": "6082cffe55cbd30000af6bf7",
      "text": "",
      "userId": "5ae7fecf7766b7001455cbd3",
      "created": 1619185663,
      "updated": 1619185663
    },
    {
      "id": "64bca6c4e600350000b44cee",
      "text": "[スタジオジブリ]",
      "userId": "62a91a7a083437001de60035",
      "created": 1690085061,
      "updated": 1690085065
    },
    {
      "id": "64bca6c5e600350000b44cef",
      "text": "",
      "userId": "62a91a7a083437001de60035",
      "created": 1690085062,
      "updated": 1690085062
    }
  ]
}