{
  "id": "61c5d8176cdfc9001d9807ed",
  "title": "好きな音",
  "created": 1640355867,
  "updated": 1640495805,
  "lines": [
    {
      "id": "61c5d8176cdfc9001d9807ed",
      "text": "好きな音",
      "userId": "59fb21121207900012774b17",
      "created": 1640355867,
      "updated": 1640355867
    },
    {
      "id": "61c5d81a774b170000455be4",
      "text": "雨の音[基素.icon]",
      "userId": "59fb21121207900012774b17",
      "created": 1640355867,
      "updated": 1640355883
    },
    {
      "id": "61c5f6e2e5172d00002ba694",
      "text": "雷の音[yosider.icon]",
      "userId": "5c30ba88e98efe0017e5172d",
      "created": 1640363746,
      "updated": 1640363750
    },
    {
      "id": "61c5f6e6e5172d00002ba695",
      "text": "肉を焼く音[yosider.icon]",
      "userId": "5c30ba88e98efe0017e5172d",
      "created": 1640363751,
      "updated": 1640363759
    },
    {
      "id": "61c5d81b774b170000455be5",
      "text": "ぜんまいを巻く音[kuuote.icon]",
      "userId": "5e8944948a182900174bb2e2",
      "created": 1640355868,
      "updated": 1640454878
    },
    {
      "id": "61c75ad64bb2e200005109a1",
      "text": "川のせせらぎ[maichan.icon]",
      "userId": "615026d6d6a2280023c3f2c7",
      "created": 1640454872,
      "updated": 1640495805
    },
    {
      "id": "61c7fabac3f2c700009bcd3f",
      "text": "",
      "userId": "615026d6d6a2280023c3f2c7",
      "created": 1640495802,
      "updated": 1640495802
    }
  ]
}