{
  "id": "63af96f0cf8d9a001d3c0cb4",
  "title": "ぜんざい",
  "created": 1672451828,
  "updated": 1672455376,
  "lines": [
    {
      "id": "63af96f0cf8d9a001d3c0cb4",
      "text": "ぜんざい",
      "userId": "5dc4278df651e0001745c7e6",
      "created": 1672451828,
      "updated": 1672451828
    },
    {
      "id": "63af96f245c7e60000523808",
      "text": ">ぜんざい（善哉）は、豆（主に[小豆]）を[砂糖]で甘く煮た日本の食べ物である。",
      "userId": "62a91a7a083437001de60035",
      "created": 1672451828,
      "updated": 1672455322
    },
    {
      "id": "63af972f45c7e6000052380a",
      "text": "> ",
      "userId": "5dc4278df651e0001745c7e6",
      "created": 1672451888,
      "updated": 1672451888
    },
    {
      "id": "63af972f45c7e6000052380b",
      "text": "> [餅]や[白玉団子]、[栗の甘露煮]などと共に供されることが多い。一般的には豆の原形が存在するものを指して用いられるが、例外もある。",
      "userId": "62a91a7a083437001de60035",
      "created": 1672451888,
      "updated": 1672455328
    },
    {
      "id": "63af972e45c7e60000523809",
      "text": "",
      "userId": "5dc4278df651e0001745c7e6",
      "created": 1672451887,
      "updated": 1672451887
    },
    {
      "id": "63af97ad45c7e60000523814",
      "text": ">関東地方では汁気のない餡そのものをぜんざいと呼ぶが、関西地方では[粒餡]を用いた温かい汁物をぜんざいと呼び、[漉し餡]を用いた汁物は「[汁粉]」と呼び分ける。",
      "userId": "62a91a7a083437001de60035",
      "created": 1672452015,
      "updated": 1672455353
    },
    {
      "id": "63af986145c7e6000052381b",
      "text": "",
      "userId": "5dc4278df651e0001745c7e6",
      "created": 1672452195,
      "updated": 1672452195
    },
    {
      "id": "63af984f45c7e60000523819",
      "text": ">[https://gyazo.com/11d426d9b7dd9487655a4c319ad15f9b]",
      "userId": "5dc4278df651e0001745c7e6",
      "created": 1672452176,
      "updated": 1672452197
    },
    {
      "id": "63af985745c7e6000052381a",
      "text": "[https://style.nikkei.com/article/DGXNASJB0702P_X01C13A1AA1P00/ 関西のぜんざい、関東ではおしるこ 呼び方なぜ違う｜NIKKEI STYLE]",
      "userId": "5dc4278df651e0001745c7e6",
      "created": 1672452185,
      "updated": 1672452209
    },
    {
      "id": "63af987045c7e6000052381c",
      "text": "",
      "userId": "5dc4278df651e0001745c7e6",
      "created": 1672452209,
      "updated": 1672452209
    },
    {
      "id": "63af988c45c7e6000052381d",
      "text": "「[おしるこ]」というワード、テレビでしか聞いたことがない気がするな...[lsajfk.icon]",
      "userId": "5dc4278df651e0001745c7e6",
      "created": 1672452237,
      "updated": 1672452266
    },
    {
      "id": "63af97c745c7e60000523817",
      "text": "",
      "userId": "5dc4278df651e0001745c7e6",
      "created": 1672452041,
      "updated": 1672452041
    },
    {
      "id": "63af974745c7e6000052380c",
      "text": "語源",
      "userId": "5dc4278df651e0001745c7e6",
      "created": 1672451913,
      "updated": 1672451915
    },
    {
      "id": "63af974a45c7e6000052380e",
      "text": "　>ぜんざいの語源は主に2説ある。",
      "userId": "5dc4278df651e0001745c7e6",
      "created": 1672451916,
      "updated": 1672451939
    },
    {
      "id": "63af976145c7e6000052380f",
      "text": " > ",
      "userId": "5dc4278df651e0001745c7e6",
      "created": 1672451939,
      "updated": 1672451939
    },
    {
      "id": "63af976145c7e60000523810",
      "text": " > 1つは[仏教]用語である「[善哉]（ぜんざい・よきかな）」を由来とする説である。[一休宗純]が最初に食べたとされ、この食べ物の美味しさに「善哉」と叫んだ事から名称とされた。「善哉」とは仏が弟子を褒める時に使う言葉であり、[サンスクリット語]の素晴らしいを意味する「[sadhu]」の漢訳である。",
      "userId": "62a91a7a083437001de60035",
      "created": 1672451939,
      "updated": 1672455303
    },
    {
      "id": "63af976145c7e60000523811",
      "text": " > ",
      "userId": "5dc4278df651e0001745c7e6",
      "created": 1672451939,
      "updated": 1672451939
    },
    {
      "id": "63af976145c7e60000523812",
      "text": " > もう1つは、出雲地方の神事「[神在祭]」で振る舞われた「[神在餅]」を由来とする説である。「神在餅」の「じんざい」が訛り、「ぜんざい」へと変化したと言われている。",
      "userId": "62a91a7a083437001de60035",
      "created": 1672451939,
      "updated": 1672455376
    },
    {
      "id": "63af974a45c7e6000052380d",
      "text": "https://ja.wikipedia.org/wiki/ぜんざい",
      "userId": "5dc4278df651e0001745c7e6",
      "created": 1672451915,
      "updated": 1672451983
    },
    {
      "id": "63af978f45c7e60000523813",
      "text": "",
      "userId": "5dc4278df651e0001745c7e6",
      "created": 1672451984,
      "updated": 1672451984
    },
    {
      "id": "63af97835e90c0000053f3bf",
      "text": "よきかなよきかな",
      "userId": "60508ed36a7abc00235e90c0",
      "created": 1672451970,
      "updated": 1672451975
    },
    {
      "id": "63af97875e90c0000053f3c0",
      "text": "",
      "userId": "60508ed36a7abc00235e90c0",
      "created": 1672451975,
      "updated": 1672451975
    }
  ]
}