{
  "id": "64709e93093e75001bac933a",
  "title": "お風呂に入るのは夕食前？夕食後？",
  "created": 1685102229,
  "updated": 1685153144,
  "lines": [
    {
      "id": "64709e93093e75001bac933a",
      "text": "お風呂に入るのは夕食前？夕食後？",
      "userId": "5f0ae250e8cd56001ee2dacc",
      "created": 1685102229,
      "updated": 1685102237
    },
    {
      "id": "64709ea8e2dacc00005a7b22",
      "text": "#お風呂",
      "userId": "60508ed36a7abc00235e90c0",
      "created": 1685102251,
      "updated": 1685108080
    },
    {
      "id": "64709ea9e2dacc00005a7b23",
      "text": "子供の頃は[夕食]前だった[nomadoor.icon]",
      "userId": "60508ed36a7abc00235e90c0",
      "created": 1685102251,
      "updated": 1685108067
    },
    {
      "id": "64709eb2e2dacc00005a7b25",
      "text": " ご飯食べて眠くなったらそのまま寝ちゃえるのが良かった",
      "userId": "5f0ae250e8cd56001ee2dacc",
      "created": 1685102260,
      "updated": 1685102281
    },
    {
      "id": "64709eabe2dacc00005a7b24",
      "text": "",
      "userId": "5f0ae250e8cd56001ee2dacc",
      "created": 1685102253,
      "updated": 1685102253
    },
    {
      "id": "6470b5986eb40600000316da",
      "text": "娘があまり夕食を食べないので、少しでも遅くしようとして、先に風呂にしてる[inajob.icon]",
      "userId": "58442db3ee4a2400116eb406",
      "created": 1685108121,
      "updated": 1685108150
    },
    {
      "id": "6470b5a16eb40600000316db",
      "text": "",
      "userId": "58442db3ee4a2400116eb406",
      "created": 1685108130,
      "updated": 1685108130
    },
    {
      "id": "64713c5d79d3a900004686bc",
      "text": "夕食後。すぐ腹減るので早く食べたい＆べたつきなるべくなくして寝たいので風呂は就寝時刻に寄せたい、でこうなった[sta.icon]",
      "userId": "5a4873ab2e26fb001479d3a9",
      "created": 1685142622,
      "updated": 1685142690
    },
    {
      "id": "64713c7279d3a900004686bd",
      "text": "",
      "userId": "5a4873ab2e26fb001479d3a9",
      "created": 1685142642,
      "updated": 1685142642
    },
    {
      "id": "64714281b043cd0000b84f0d",
      "text": "夕食後。お風呂に入るのが面倒で先延ばししてしまうから早く入る事ができない[kutsumofu.icon]",
      "userId": "6258de7c75b8d2001db043cd",
      "created": 1685144194,
      "updated": 1685144248
    },
    {
      "id": "64714284b043cd0000b84f0e",
      "text": "",
      "userId": "6258de7c75b8d2001db043cd",
      "created": 1685144197,
      "updated": 1685144197
    },
    {
      "id": "64714e53c3f2c70000fb182b",
      "text": "夕食前[maichan.icon]",
      "userId": "615026d6d6a2280023c3f2c7",
      "created": 1685147114,
      "updated": 1685147120
    },
    {
      "id": "64714e5ac3f2c70000fb182d",
      "text": "　仕事から帰ったらすぐお風呂に入ってリセットしたい",
      "userId": "615026d6d6a2280023c3f2c7",
      "created": 1685147121,
      "updated": 1685147225
    },
    {
      "id": "64714ec3c3f2c70000fb182f",
      "text": "　夕食が結構遅いのでその後でお風呂だと遅くなってしまう",
      "userId": "615026d6d6a2280023c3f2c7",
      "created": 1685147226,
      "updated": 1685147290
    },
    {
      "id": "64714e58c3f2c70000fb182c",
      "text": "",
      "userId": "615026d6d6a2280023c3f2c7",
      "created": 1685147119,
      "updated": 1685147119
    },
    {
      "id": "6471549471fa08000096b46f",
      "text": "朝に入るので朝食前[biwachi.icon]",
      "userId": "62c8e96f1f5ebf001d71fa08",
      "created": 1685148821,
      "updated": 1685148830
    },
    {
      "id": "6471549471fa08000096b470",
      "text": "",
      "userId": "62c8e96f1f5ebf001d71fa08",
      "created": 1685148821,
      "updated": 1685148821
    },
    {
      "id": "647158f0b8bbfc00006d57df",
      "text": "夕食後だと思っている[はるひ.icon]",
      "userId": "60c9f2f6c225a50020b8bbfc",
      "created": 1685149937,
      "updated": 1685150136
    },
    {
      "id": "647158f3b8bbfc00006d57e1",
      "text": "\tうちはそういう習慣だった",
      "userId": "60c9f2f6c225a50020b8bbfc",
      "created": 1685149940,
      "updated": 1685149950
    },
    {
      "id": "647159beb8bbfc00006d57e8",
      "text": "\t温泉は入った後に浴衣でご飯ですよね",
      "userId": "60c9f2f6c225a50020b8bbfc",
      "created": 1685150142,
      "updated": 1685150159
    },
    {
      "id": "64715900b8bbfc00006d57e3",
      "text": "\tひとり暮らしを始めてからは夕食の習慣がなくなったので不定",
      "userId": "60c9f2f6c225a50020b8bbfc",
      "created": 1685149953,
      "updated": 1685150015
    },
    {
      "id": "6471591fb8bbfc00006d57e4",
      "text": "\t\t一応入浴は毎日2220～と決めているがたいてい入りたい時に入ってしまうのでさらに不定",
      "userId": "60c9f2f6c225a50020b8bbfc",
      "created": 1685149984,
      "updated": 1685150120
    },
    {
      "id": "64715952b8bbfc00006d57e6",
      "text": "\t\tあまり把握してないが、一日2～3回入ってるかも？なのでさらに不定",
      "userId": "60c9f2f6c225a50020b8bbfc",
      "created": 1685150035,
      "updated": 1685150121
    },
    {
      "id": "647158f3b8bbfc00006d57e0",
      "text": "",
      "userId": "60c9f2f6c225a50020b8bbfc",
      "created": 1685149940,
      "updated": 1685149940
    },
    {
      "id": "6471655a7838e30000c7e325",
      "text": "[朝風呂]派[Mijinko_SD.icon]",
      "userId": "60fb0a79f3364000237838e3",
      "created": 1685153115,
      "updated": 1685153144
    },
    {
      "id": "647165637838e30000c7e327",
      "text": "　寝てても汚れるし",
      "userId": "60fb0a79f3364000237838e3",
      "created": 1685153124,
      "updated": 1685153129
    },
    {
      "id": "6471655e7838e30000c7e326",
      "text": "",
      "userId": "60fb0a79f3364000237838e3",
      "created": 1685153119,
      "updated": 1685153119
    }
  ]
}