{
  "id": "6496f2730979f0001c3e0161",
  "title": "atelier basi",
  "created": 1687614073,
  "updated": 1687614818,
  "lines": [
    {
      "id": "6496f2730979f0001c3e0161",
      "text": "atelier basi",
      "userId": "5d89b1f60230ae001779e113",
      "created": 1687614073,
      "updated": 1687614073
    },
    {
      "id": "6496f27f79e1130000888771",
      "text": "　[米国大受験], [海外留学]に興味がある高校生をサポートする団体",
      "userId": "5d89b1f60230ae001779e113",
      "created": 1687614080,
      "updated": 1687614112
    },
    {
      "id": "6496f29f79e1130000888773",
      "text": "　　運営・メンターをやっている[blu3mo.icon]",
      "userId": "5d89b1f60230ae001779e113",
      "created": 1687614112,
      "updated": 1687614121
    },
    {
      "id": "6496f54b79e1130000888781",
      "text": "",
      "userId": "5d89b1f60230ae001779e113",
      "created": 1687614796,
      "updated": 1687614796
    },
    {
      "id": "6496f54b79e1130000888782",
      "text": " 知り合いに海外大進学興味ある高校生などいればシェアしてもらえると嬉しいです〜",
      "userId": "5d89b1f60230ae001779e113",
      "created": 1687614796,
      "updated": 1687614806
    },
    {
      "id": "6496f55679e1130000888783",
      "text": " 　Twitterでは届かない層にリーチしたい",
      "userId": "5d89b1f60230ae001779e113",
      "created": 1687614806,
      "updated": 1687614818
    },
    {
      "id": "6496f27f79e1130000888772",
      "text": "",
      "userId": "5d89b1f60230ae001779e113",
      "created": 1687614080,
      "updated": 1687614790
    },
    {
      "id": "6496f27879e1130000888768",
      "text": ">[https://twitter.com/AtelierBasi/status/1672601920303943681 @AtelierBasi]: 【atelier basi・2023年度プログラム受講生・募集開始！】",
      "userId": "5d89b1f60230ae001779e113",
      "created": 1687614073,
      "updated": 1687614785
    },
    {
      "id": "6496f53c79e1130000888778",
      "text": ">全国各地の熱意ある高校生が環境に負けない進学が出来るよう、海外大進学を無償でサポートします。",
      "userId": "5d89b1f60230ae001779e113",
      "created": 1687614781,
      "updated": 1687614781
    },
    {
      "id": "6496f53c79e1130000888779",
      "text": ">締切：2023年7月4日（火）23:59 JST",
      "userId": "5d89b1f60230ae001779e113",
      "created": 1687614781,
      "updated": 1687614781
    },
    {
      "id": "6496f53c79e113000088877a",
      "text": ">以下のフォームよりご応募ください。",
      "userId": "5d89b1f60230ae001779e113",
      "created": 1687614781,
      "updated": 1687614781
    },
    {
      "id": "6496f53c79e113000088877b",
      "text": ">ご応募お待ちしております！",
      "userId": "5d89b1f60230ae001779e113",
      "created": 1687614781,
      "updated": 1687614781
    },
    {
      "id": "6496f53c79e113000088877c",
      "text": ">https://t.co/FagSvoiwZ4",
      "userId": "5d89b1f60230ae001779e113",
      "created": 1687614781,
      "updated": 1687614781
    },
    {
      "id": "6496f53c79e113000088877d",
      "text": ">[https://pbs.twimg.com/media/FzZGkfiagAcTqZC.jpg]",
      "userId": "5d89b1f60230ae001779e113",
      "created": 1687614781,
      "updated": 1687614781
    },
    {
      "id": "6496f54479e113000088877f",
      "text": "",
      "userId": "5d89b1f60230ae001779e113",
      "created": 1687614789,
      "updated": 1687614789
    },
    {
      "id": "6496f54479e1130000888780",
      "text": "",
      "userId": "5d89b1f60230ae001779e113",
      "created": 1687614789,
      "updated": 1687614789
    }
  ]
}