{
  "id": "66dfacf07be6a9001c4491be",
  "title": "ガベコレ",
  "created": 1725934833,
  "updated": 1725934838,
  "lines": [
    {
      "id": "66dfacf07be6a9001c4491be",
      "text": "ガベコレ",
      "userId": "62919f6444e78d001d73e522",
      "created": 1725934833,
      "updated": 1725934833
    },
    {
      "id": "66dfacf173e522000037fa03",
      "text": "[ガベージコレクション]",
      "userId": "62919f6444e78d001d73e522",
      "created": 1725934833,
      "updated": 1725934838
    },
    {
      "id": "66dfacf273e522000037fa04",
      "text": "",
      "userId": "62919f6444e78d001d73e522",
      "created": 1725934834,
      "updated": 1725934834
    }
  ]
}