{
  "id": "67c8246cd65e3a7644f8af7c",
  "title": "新語流行語大賞",
  "created": 1741169773,
  "updated": 1741169812,
  "lines": [
    {
      "id": "67c8246cd65e3a7644f8af7c",
      "text": "新語流行語大賞",
      "userId": "5b5e7121417cf700145b98c2",
      "created": 1741169773,
      "updated": 1741169773
    },
    {
      "id": "67c8246d5b98c200009dd55e",
      "text": "https://www.jiyu.co.jp/singo/",
      "userId": "5b5e7121417cf700145b98c2",
      "created": 1741169773,
      "updated": 1741169775
    },
    {
      "id": "67c8246e5b98c200009dd560",
      "text": "https://ja.wikipedia.org/wiki/新語・流行語大賞",
      "userId": "5b5e7121417cf700145b98c2",
      "created": 1741169775,
      "updated": 1741169775
    },
    {
      "id": "67c8246e5b98c200009dd561",
      "text": "",
      "userId": "5b5e7121417cf700145b98c2",
      "created": 1741169775,
      "updated": 1741169775
    },
    {
      "id": "67c824775b98c200009dd562",
      "text": "[流行っていない流行語]",
      "userId": "5b5e7121417cf700145b98c2",
      "created": 1741169784,
      "updated": 1741169801
    }
  ]
}