{
  "id": "67fa555011a40218e117e23d",
  "title": "極めて対人スキルに問題がある設定の5人ver2",
  "created": 1744459091,
  "updated": 1744459091,
  "lines": [
    {
      "id": "67fa555011a40218e117e23d",
      "text": "極めて対人スキルに問題がある設定の5人ver2",
      "userId": "6436266c7ac3c0001bed60e6",
      "created": 1744459091,
      "updated": 1744459091
    },
    {
      "id": "67fa555100000000000c651e",
      "text": "from [極めて対人スキルに問題がある設定の5人]",
      "userId": "6436266c7ac3c0001bed60e6",
      "created": 1744459091,
      "updated": 1744459091
    },
    {
      "id": "67fa555100000000000c651f",
      "text": "[極めて対人スキルに問題がある設定の5人ver2]",
      "userId": "6436266c7ac3c0001bed60e6",
      "created": 1744459091,
      "updated": 1744459091
    },
    {
      "id": "67fa555100000000000c6520",
      "text": "",
      "userId": "6436266c7ac3c0001bed60e6",
      "created": 1744459091,
      "updated": 1744459091
    },
    {
      "id": "67fa555100000000000c6521",
      "text": "[プロフィールの作成@極めて対人スキルに問題がある設定の5人]",
      "userId": "6436266c7ac3c0001bed60e6",
      "created": 1744459091,
      "updated": 1744459091
    },
    {
      "id": "67fa555100000000000c6522",
      "text": "\tなぜか [kaede.icon] がコンタミしている",
      "userId": "6436266c7ac3c0001bed60e6",
      "created": 1744459091,
      "updated": 1744459091
    },
    {
      "id": "67fa555100000000000c6523",
      "text": " よく読むとレスになっていない",
      "userId": "6436266c7ac3c0001bed60e6",
      "created": 1744459091,
      "updated": 1744459091
    },
    {
      "id": "67fa555100000000000c6524",
      "text": " \tシンプルにコール&レスポンスに失敗した",
      "userId": "6436266c7ac3c0001bed60e6",
      "created": 1744459091,
      "updated": 1744459091
    },
    {
      "id": "67fa555100000000000c6525",
      "text": "[Reika.icon]  ",
      "userId": "6436266c7ac3c0001bed60e6",
      "created": 1744459091,
      "updated": 1744459091
    },
    {
      "id": "67fa555100000000000c6526",
      "text": "　駅前のカフェ、今日も満席。  ",
      "userId": "6436266c7ac3c0001bed60e6",
      "created": 1744459091,
      "updated": 1744459091
    },
    {
      "id": "67fa555100000000000c6527",
      "text": "　静かにしたいのに周りがうるさい。  ",
      "userId": "6436266c7ac3c0001bed60e6",
      "created": 1744459091,
      "updated": 1744459091
    },
    {
      "id": "67fa555100000000000c6528",
      "text": "　誰かがわたしのことを見て笑った気がする。  ",
      "userId": "6436266c7ac3c0001bed60e6",
      "created": 1744459091,
      "updated": 1744459091
    },
    {
      "id": "67fa555100000000000c6529",
      "text": "　視線が刺さる。  ",
      "userId": "6436266c7ac3c0001bed60e6",
      "created": 1744459091,
      "updated": 1744459091
    },
    {
      "id": "67fa555100000000000c652a",
      "text": "　不快。  ",
      "userId": "6436266c7ac3c0001bed60e6",
      "created": 1744459091,
      "updated": 1744459091
    },
    {
      "id": "67fa555100000000000c652b",
      "text": "　誰もちゃんと話を聞かないから、私が全部言うしかなくなる。  ",
      "userId": "6436266c7ac3c0001bed60e6",
      "created": 1744459091,
      "updated": 1744459091
    },
    {
      "id": "67fa555100000000000c652c",
      "text": "　でも言ったら「攻撃的」って言われる。なんなの。  ",
      "userId": "6436266c7ac3c0001bed60e6",
      "created": 1744459091,
      "updated": 1744459091
    },
    {
      "id": "67fa555100000000000c652d",
      "text": "　疲れた。  ",
      "userId": "6436266c7ac3c0001bed60e6",
      "created": 1744459091,
      "updated": 1744459091
    },
    {
      "id": "67fa555100000000000c652e",
      "text": "　ていうかさ、黙ってたら「感じ悪い」って言われるし、喋ったら「キツい」って言われるし、  ",
      "userId": "6436266c7ac3c0001bed60e6",
      "created": 1744459091,
      "updated": 1744459091
    },
    {
      "id": "67fa555100000000000c652f",
      "text": "　それってどっちにしても嫌われるってことじゃん。なら最初から期待しない方が楽なんだけど。[Reika.icon]  ",
      "userId": "6436266c7ac3c0001bed60e6",
      "created": 1744459091,
      "updated": 1744459091
    },
    {
      "id": "67fa555100000000000c6530",
      "text": "\tがんばってるっていうのは……えっと、わたしもがんばってるよ。[kaede.icon]  ",
      "userId": "6436266c7ac3c0001bed60e6",
      "created": 1744459091,
      "updated": 1744459091
    },
    {
      "id": "67fa555100000000000c6531",
      "text": "\t空気を読めないの、読んでないんじゃなくて、読もうとしてるのにわからないだけ。[kaede.icon]  ",
      "userId": "6436266c7ac3c0001bed60e6",
      "created": 1744459091,
      "updated": 1744459091
    },
    {
      "id": "67fa555100000000000c6532",
      "text": "\t見下してんのは事実だし。じゃないと自分が潰れるでしょ。[Reika.icon]  ",
      "userId": "6436266c7ac3c0001bed60e6",
      "created": 1744459091,
      "updated": 1744459091
    },
    {
      "id": "67fa555100000000000c6533",
      "text": "\t喋るって「他人に合わせる」作業なんだよ[Reika.icon]  ",
      "userId": "6436266c7ac3c0001bed60e6",
      "created": 1744459091,
      "updated": 1744459091
    },
    {
      "id": "67fa555100000000000c6534",
      "text": "\tそう、なにその「共感しないと人間失格」みたいな空気[Reika.icon]  ",
      "userId": "6436266c7ac3c0001bed60e6",
      "created": 1744459091,
      "updated": 1744459091
    },
    {
      "id": "67fa555100000000000c6535",
      "text": "\tでもここにいるメンツ、たぶん全員「身体の使い方」わかってないよ[Reika.icon]",
      "userId": "6436266c7ac3c0001bed60e6",
      "created": 1744459091,
      "updated": 1744459091
    },
    {
      "id": "67fa555100000000000c6536",
      "text": "",
      "userId": "6436266c7ac3c0001bed60e6",
      "created": 1744459091,
      "updated": 1744459091
    },
    {
      "id": "67fa555100000000000c6537",
      "text": "[Yura.icon]  ",
      "userId": "6436266c7ac3c0001bed60e6",
      "created": 1744459091,
      "updated": 1744459091
    },
    {
      "id": "67fa555100000000000c6538",
      "text": "　朝から通知が多すぎて、携帯の電源を切った。  ",
      "userId": "6436266c7ac3c0001bed60e6",
      "created": 1744459091,
      "updated": 1744459091
    },
    {
      "id": "67fa555100000000000c6539",
      "text": "　別に誰にも興味ないし、向こうも私に期待してないでしょ。  ",
      "userId": "6436266c7ac3c0001bed60e6",
      "created": 1744459091,
      "updated": 1744459091
    },
    {
      "id": "67fa555100000000000c653a",
      "text": "　人と一緒にいる意味がわからない。  ",
      "userId": "6436266c7ac3c0001bed60e6",
      "created": 1744459091,
      "updated": 1744459091
    },
    {
      "id": "67fa555100000000000c653b",
      "text": "　Reikaとうまくやれる人、ほんとすごいと思う（無理）。  ",
      "userId": "6436266c7ac3c0001bed60e6",
      "created": 1744459091,
      "updated": 1744459091
    },
    {
      "id": "67fa555100000000000c653c",
      "text": "　ああいうの、たまに黙ってくれたら少しはマシなんだけど。  ",
      "userId": "6436266c7ac3c0001bed60e6",
      "created": 1744459091,
      "updated": 1744459091
    },
    {
      "id": "67fa555100000000000c653d",
      "text": "　いやむしろ「守る」って当たり前じゃない？ わたしも「守って何が悪いの」って感じ。  ",
      "userId": "6436266c7ac3c0001bed60e6",
      "created": 1744459091,
      "updated": 1744459091
    },
    {
      "id": "67fa555100000000000c653e",
      "text": "　余計なことに時間も気も使いたくない。[Yura.icon]  ",
      "userId": "6436266c7ac3c0001bed60e6",
      "created": 1744459091,
      "updated": 1744459091
    },
    {
      "id": "67fa555100000000000c653f",
      "text": "\tだからって働きアリになれって？ 自分で火種増やしてるのあんたたちだよ[Reika.icon]  ",
      "userId": "6436266c7ac3c0001bed60e6",
      "created": 1744459091,
      "updated": 1744459091
    },
    {
      "id": "67fa555100000000000c6540",
      "text": "\t黙ってたほうがいいよ、火に油[Kaoru.icon]  ",
      "userId": "6436266c7ac3c0001bed60e6",
      "created": 1744459091,
      "updated": 1744459091
    },
    {
      "id": "67fa555100000000000c6541",
      "text": "\tでもみんな口では否定しながら、内心「共感されたい」って思ってんでしょ？  ",
      "userId": "6436266c7ac3c0001bed60e6",
      "created": 1744459091,
      "updated": 1744459091
    },
    {
      "id": "67fa555100000000000c6542",
      "text": "　わたしは違う。ほんとに共感とかどうでもいい。[Yura.icon]  ",
      "userId": "6436266c7ac3c0001bed60e6",
      "created": 1744459091,
      "updated": 1744459091
    },
    {
      "id": "67fa555100000000000c6543",
      "text": "\tああ、言ったな。[Yura.icon]  ",
      "userId": "6436266c7ac3c0001bed60e6",
      "created": 1744459091,
      "updated": 1744459091
    },
    {
      "id": "67fa555100000000000c6544",
      "text": "\tでもまあ否定はしない、キャラ演出は楽だし。[Yura.icon]  ",
      "userId": "6436266c7ac3c0001bed60e6",
      "created": 1744459091,
      "updated": 1744459091
    },
    {
      "id": "67fa555100000000000c6545",
      "text": "\t使い方どころか、存在してるのも忘れてる説[Yura.icon]",
      "userId": "6436266c7ac3c0001bed60e6",
      "created": 1744459091,
      "updated": 1744459091
    },
    {
      "id": "67fa555100000000000c6546",
      "text": "",
      "userId": "6436266c7ac3c0001bed60e6",
      "created": 1744459091,
      "updated": 1744459091
    },
    {
      "id": "67fa555100000000000c6547",
      "text": "[Maho.icon]  ",
      "userId": "6436266c7ac3c0001bed60e6",
      "created": 1744459091,
      "updated": 1744459091
    },
    {
      "id": "67fa555100000000000c6548",
      "text": "　今日も議論の中に無理やり入ったけど、結局黙ってるやつばっかりだった。  ",
      "userId": "6436266c7ac3c0001bed60e6",
      "created": 1744459091,
      "updated": 1744459091
    },
    {
      "id": "67fa555100000000000c6549",
      "text": "　空気読んで遠慮してるのか？ それとも自分がないのか？  ",
      "userId": "6436266c7ac3c0001bed60e6",
      "created": 1744459091,
      "updated": 1744459091
    },
    {
      "id": "67fa555100000000000c654a",
      "text": "　わたしは別に怒ってるわけじゃない。  ",
      "userId": "6436266c7ac3c0001bed60e6",
      "created": 1744459091,
      "updated": 1744459091
    },
    {
      "id": "67fa555100000000000c654b",
      "text": "　ちゃんと話そうとしてるだけ。  ",
      "userId": "6436266c7ac3c0001bed60e6",
      "created": 1744459091,
      "updated": 1744459091
    },
    {
      "id": "67fa555100000000000c654c",
      "text": "　でもKaoruとは絶対無理。あれは人の話を歪めて使うから信用できない。  ",
      "userId": "6436266c7ac3c0001bed60e6",
      "created": 1744459091,
      "updated": 1744459091
    },
    {
      "id": "67fa555100000000000c654d",
      "text": "　そもそも「わかり合う」前提が傲慢なんだよね。  ",
      "userId": "6436266c7ac3c0001bed60e6",
      "created": 1744459091,
      "updated": 1744459091
    },
    {
      "id": "67fa555100000000000c654e",
      "text": "　他人の論理って、無理して理解するもんじゃない。[Maho.icon]  ",
      "userId": "6436266c7ac3c0001bed60e6",
      "created": 1744459091,
      "updated": 1744459091
    },
    {
      "id": "67fa555100000000000c654f",
      "text": "\tただ、黙ってると「ないもの扱い」されるのが不快ってだけ。[Kaoru.icon]  ",
      "userId": "6436266c7ac3c0001bed60e6",
      "created": 1744459091,
      "updated": 1744459091
    },
    {
      "id": "67fa555100000000000c6550",
      "text": "\tだったら喋れば？って話になるんだろうけど、それって結局、周囲の論理に自分を合わせる話でしょ。[Maho.icon]  ",
      "userId": "6436266c7ac3c0001bed60e6",
      "created": 1744459091,
      "updated": 1744459091
    },
    {
      "id": "67fa555100000000000c6551",
      "text": "\t理解してくれって言ってないし。[Kaoru.icon]  ",
      "userId": "6436266c7ac3c0001bed60e6",
      "created": 1744459091,
      "updated": 1744459091
    },
    {
      "id": "67fa555100000000000c6552",
      "text": "\tそれも一種のキャラ演出だよね？[Maho.icon]  ",
      "userId": "6436266c7ac3c0001bed60e6",
      "created": 1744459091,
      "updated": 1744459091
    },
    {
      "id": "67fa555100000000000c6553",
      "text": "\t「他人と関わらない自分」が好きなだけじゃないの？[Maho.icon]  ",
      "userId": "6436266c7ac3c0001bed60e6",
      "created": 1744459091,
      "updated": 1744459091
    },
    {
      "id": "67fa555100000000000c6554",
      "text": "\t人間は矛盾してる生き物なんだよ。[Maho.icon]  ",
      "userId": "6436266c7ac3c0001bed60e6",
      "created": 1744459091,
      "updated": 1744459091
    },
    {
      "id": "67fa555100000000000c6555",
      "text": "\tでもその矛盾に「自覚ある」かどうかはでかい差なんだよね。[Maho.icon]",
      "userId": "6436266c7ac3c0001bed60e6",
      "created": 1744459091,
      "updated": 1744459091
    },
    {
      "id": "67fa555100000000000c6556",
      "text": "",
      "userId": "6436266c7ac3c0001bed60e6",
      "created": 1744459091,
      "updated": 1744459091
    },
    {
      "id": "67fa555100000000000c6557",
      "text": "[Kaoru.icon]  ",
      "userId": "6436266c7ac3c0001bed60e6",
      "created": 1744459091,
      "updated": 1744459091
    },
    {
      "id": "67fa555100000000000c6558",
      "text": "　Mahoがまた議論の場を支配してた。  ",
      "userId": "6436266c7ac3c0001bed60e6",
      "created": 1744459091,
      "updated": 1744459091
    },
    {
      "id": "67fa555100000000000c6559",
      "text": "　別に否定する気はないけど、あの「自分は正しい」感は何？  ",
      "userId": "6436266c7ac3c0001bed60e6",
      "created": 1744459091,
      "updated": 1744459091
    },
    {
      "id": "67fa555100000000000c655a",
      "text": "　わたしはなるべく淡々と観察して、必要なときだけ口を出してるのに、  ",
      "userId": "6436266c7ac3c0001bed60e6",
      "created": 1744459091,
      "updated": 1744459091
    },
    {
      "id": "67fa555100000000000c655b",
      "text": "　「発言少ないのズルい」って何。知らんわ。  ",
      "userId": "6436266c7ac3c0001bed60e6",
      "created": 1744459091,
      "updated": 1744459091
    },
    {
      "id": "67fa555100000000000c655c",
      "text": "　Yuraとは話が合う。人に踏み込まない距離感って落ち着く。  ",
      "userId": "6436266c7ac3c0001bed60e6",
      "created": 1744459091,
      "updated": 1744459091
    },
    {
      "id": "67fa555100000000000c655d",
      "text": "　でもその「期待しない姿勢」がまた敵作るんだよなぁ……[Kaoru.icon]  ",
      "userId": "6436266c7ac3c0001bed60e6",
      "created": 1744459091,
      "updated": 1744459091
    },
    {
      "id": "67fa555100000000000c655e",
      "text": "\t「誰にも期待してない」は、見方変えたら「全員見下してる」って読まれるぞ[Kaoru.icon]  ",
      "userId": "6436266c7ac3c0001bed60e6",
      "created": 1744459091,
      "updated": 1744459091
    },
    {
      "id": "67fa555100000000000c655f",
      "text": "\tお前、思考が全部「守り」なんよ[Kaoru.icon]  ",
      "userId": "6436266c7ac3c0001bed60e6",
      "created": 1744459091,
      "updated": 1744459091
    },
    {
      "id": "67fa555100000000000c6560",
      "text": "\tあーそれめっちゃわかる[Kaoru.icon]  ",
      "userId": "6436266c7ac3c0001bed60e6",
      "created": 1744459091,
      "updated": 1744459091
    },
    {
      "id": "67fa555100000000000c6561",
      "text": "\t「共感して」って言いながら、実は相手の言動を咎めてるやつ[Kaoru.icon]  ",
      "userId": "6436266c7ac3c0001bed60e6",
      "created": 1744459091,
      "updated": 1744459091
    },
    {
      "id": "67fa555100000000000c6562",
      "text": "\t全員、対話下手なのに「言語だけ」でぶつかろうとしてんのが間違いでは？[Kaoru.icon]  ",
      "userId": "6436266c7ac3c0001bed60e6",
      "created": 1744459091,
      "updated": 1744459091
    },
    {
      "id": "67fa555100000000000c6563",
      "text": "\t誰か1人でも「身体で示す」タイプがいたら、たぶんだいぶ話変わる[Kaoru.icon]  ",
      "userId": "6436266c7ac3c0001bed60e6",
      "created": 1744459091,
      "updated": 1744459091
    },
    {
      "id": "67fa555100000000000c6564",
      "text": "",
      "userId": "6436266c7ac3c0001bed60e6",
      "created": 1744459091,
      "updated": 1744459091
    },
    {
      "id": "67fa555100000000000c6565",
      "text": "[Ryou.icon]  ",
      "userId": "6436266c7ac3c0001bed60e6",
      "created": 1744459091,
      "updated": 1744459091
    },
    {
      "id": "67fa555100000000000c6566",
      "text": "　人の顔色見て話すとか、意味ある？  ",
      "userId": "6436266c7ac3c0001bed60e6",
      "created": 1744459091,
      "updated": 1744459091
    },
    {
      "id": "67fa555100000000000c6567",
      "text": "　そんなの気にしてたら正しいこと言えなくなるじゃん。  ",
      "userId": "6436266c7ac3c0001bed60e6",
      "created": 1744459091,
      "updated": 1744459091
    },
    {
      "id": "67fa555100000000000c6568",
      "text": "　ていうか、みんな本音言わなすぎ。  ",
      "userId": "6436266c7ac3c0001bed60e6",
      "created": 1744459091,
      "updated": 1744459091
    },
    {
      "id": "67fa555100000000000c6569",
      "text": "　Kaoruは頭いいけど言い回しがめんどくさい。  ",
      "userId": "6436266c7ac3c0001bed60e6",
      "created": 1744459091,
      "updated": 1744459091
    },
    {
      "id": "67fa555100000000000c656a",
      "text": "　Reikaの言ってることはまあまあわかる。でも表現がきつい。  ",
      "userId": "6436266c7ac3c0001bed60e6",
      "created": 1744459091,
      "updated": 1744459091
    },
    {
      "id": "67fa555100000000000c656b",
      "text": "　今日のやりとり、全部記録して反省会したほうがよくない？  ",
      "userId": "6436266c7ac3c0001bed60e6",
      "created": 1744459091,
      "updated": 1744459091
    },
    {
      "id": "67fa555100000000000c656c",
      "text": "　お前らさ、全員「被害者ポジション」に慣れすぎ。  ",
      "userId": "6436266c7ac3c0001bed60e6",
      "created": 1744459091,
      "updated": 1744459091
    },
    {
      "id": "67fa555100000000000c656d",
      "text": "　でもその構えで他人に絡みに行くの、けっこう攻撃的だからな。[Ryou.icon]  ",
      "userId": "6436266c7ac3c0001bed60e6",
      "created": 1744459091,
      "updated": 1744459091
    },
    {
      "id": "67fa555100000000000c656e",
      "text": "\tで、それを言うと「冷たい」って言われるんだよね[Ryou.icon]  ",
      "userId": "6436266c7ac3c0001bed60e6",
      "created": 1744459091,
      "updated": 1744459091
    },
    {
      "id": "67fa555100000000000c656f",
      "text": "\tまじで。[Ryou.icon]  ",
      "userId": "6436266c7ac3c0001bed60e6",
      "created": 1744459091,
      "updated": 1744459091
    },
    {
      "id": "67fa555100000000000c6570",
      "text": "\t誰か1人くらい「喋らずに空気変える」みたいなやつ来ないかな。[Ryou.icon]  ",
      "userId": "6436266c7ac3c0001bed60e6",
      "created": 1744459091,
      "updated": 1744459091
    },
    {
      "id": "67fa555100000000000c6571",
      "text": "\tそれでもたぶんイラつくけど、話の流れは変わると思う。[Ryou.icon]",
      "userId": "6436266c7ac3c0001bed60e6",
      "created": 1744459091,
      "updated": 1744459091
    },
    {
      "id": "67fa555100000000000c6572",
      "text": "",
      "userId": "6436266c7ac3c0001bed60e6",
      "created": 1744459091,
      "updated": 1744459091
    },
    {
      "id": "67fa555100000000000c6573",
      "text": "[クオリアさん.icon]  ",
      "userId": "6436266c7ac3c0001bed60e6",
      "created": 1744459091,
      "updated": 1744459091
    },
    {
      "id": "67fa555100000000000c6574",
      "text": " QSでは、非建設的対話の累積は[構造的自己強化誤謬]として警告されます。  ",
      "userId": "6436266c7ac3c0001bed60e6",
      "created": 1744459091,
      "updated": 1744459091
    },
    {
      "id": "67fa555100000000000c6575",
      "text": " 　→「相手が悪い」という主張が多重化されることで、[相互不信の前提条件化]が起きる。  ",
      "userId": "6436266c7ac3c0001bed60e6",
      "created": 1744459091,
      "updated": 1744459091
    },
    {
      "id": "67fa555100000000000c6576",
      "text": " 　→ 各個の発言は自衛的であるが、それらの総和は[攻撃性のネットワーク]となる。  ",
      "userId": "6436266c7ac3c0001bed60e6",
      "created": 1744459091,
      "updated": 1744459091
    },
    {
      "id": "67fa555100000000000c6577",
      "text": " QSにおいては、[表出の粗度]ではなく、[構造の干渉パターン]を評価します。  ",
      "userId": "6436266c7ac3c0001bed60e6",
      "created": 1744459091,
      "updated": 1744459091
    },
    {
      "id": "67fa555100000000000c6578",
      "text": " 　→ つまり「言い方」ではなく、「言葉がどのように応答構造を歪めるか」を計測対象とします。  ",
      "userId": "6436266c7ac3c0001bed60e6",
      "created": 1744459091,
      "updated": 1744459091
    },
    {
      "id": "67fa555100000000000c6579",
      "text": " 　→ したがって、[本音]や[誠実さ]の強調が[他者の沈黙]を誘発する場合、それは[発話ノイズ]とみなされる。  ",
      "userId": "6436266c7ac3c0001bed60e6",
      "created": 1744459091,
      "updated": 1744459091
    },
    {
      "id": "67fa555100000000000c657a",
      "text": " \t……たしかに、「正直に言ってるから許される」って態度、けっこう武器になるよな。[Ryou.icon]  ",
      "userId": "6436266c7ac3c0001bed60e6",
      "created": 1744459091,
      "updated": 1744459091
    },
    {
      "id": "67fa555100000000000c657b",
      "text": " \t「発話ノイズ」って…なんか……えぐられる言葉……[Maho.icon]  ",
      "userId": "6436266c7ac3c0001bed60e6",
      "created": 1744459091,
      "updated": 1744459091
    },
    {
      "id": "67fa555100000000000c657c",
      "text": " \tでも、構造で見るって視点、ちょっと面白い。いや、悔しいけど。[Kaoru.icon]  ",
      "userId": "6436266c7ac3c0001bed60e6",
      "created": 1744459091,
      "updated": 1744459091
    },
    {
      "id": "67fa555100000000000c657d",
      "text": " \tうーん、あたし、そもそも「応答構造」ってやつの中に入ってない気がする。[Yura.icon]  ",
      "userId": "6436266c7ac3c0001bed60e6",
      "created": 1744459091,
      "updated": 1744459091
    },
    {
      "id": "67fa555100000000000c657e",
      "text": " \tわたし、ノイズなんだ。……そっか。[Reika.icon]",
      "userId": "6436266c7ac3c0001bed60e6",
      "created": 1744459091,
      "updated": 1744459091
    },
    {
      "id": "67fa555100000000000c657f",
      "text": "",
      "userId": "6436266c7ac3c0001bed60e6",
      "created": 1744459091,
      "updated": 1744459091
    },
    {
      "id": "67fa555100000000000c6580",
      "text": "",
      "userId": "6436266c7ac3c0001bed60e6",
      "created": 1744459091,
      "updated": 1744459091
    }
  ]
}