{
  "id": "6948d2c198810647136525bf",
  "title": "シリアスゲーム",
  "created": 1766380227,
  "updated": 1766380467,
  "lines": [
    {
      "id": "6948d2c198810647136525bf",
      "text": "シリアスゲーム",
      "userId": "60c9f2f6c225a50020b8bbfc",
      "created": 1766380227,
      "updated": 1766380227
    },
    {
      "id": "6948d2c30000000000b2af2d",
      "text": "教育・ビジネス研修、社会問題解決に役立てるといった真面目な目的で遊ぶことを意図して作られたゲーム",
      "userId": "60c9f2f6c225a50020b8bbfc",
      "created": 1766380227,
      "updated": 1766380417
    },
    {
      "id": "6948d3b20000000000b2af35",
      "text": " [The Oregon Trail]",
      "userId": "60c9f2f6c225a50020b8bbfc",
      "created": 1766380467,
      "updated": 1766380467
    },
    {
      "id": "6948d2cb0000000000b2af2e",
      "text": " 業務シミュレーターなど",
      "userId": "60c9f2f6c225a50020b8bbfc",
      "created": 1766380236,
      "updated": 1766380430
    },
    {
      "id": "6948d38d0000000000b2af30",
      "text": " 遊んで学べる系",
      "userId": "60c9f2f6c225a50020b8bbfc",
      "created": 1766380430,
      "updated": 1766380433
    },
    {
      "id": "6948d33c0000000000b2af2f",
      "text": "",
      "userId": "60c9f2f6c225a50020b8bbfc",
      "created": 1766380348,
      "updated": 1766380348
    }
  ]
}