{
  "id": "69f44f70d4c66c06bea277ba",
  "title": "びゃあ゛ぁ゛゛ぁうまひぃ゛ぃぃ゛",
  "created": 1777618811,
  "updated": 1777618903,
  "lines": [
    {
      "id": "69f44f70d4c66c06bea277ba",
      "text": "びゃあ゛ぁ゛゛ぁうまひぃ゛ぃぃ゛",
      "userId": "5d69dde930e3c500170f1ffd",
      "created": 1777618811,
      "updated": 1777618811
    },
    {
      "id": "69f44f7a00000000000f6e11",
      "text": "> アニメ「[サザエさん]」で[マスオさん]が発したセリフ。本来は『いやぁうまい』と発言している。",
      "userId": "5d69dde930e3c500170f1ffd",
      "created": 1777618811,
      "updated": 1777618903
    },
    {
      "id": "69f44fac00000000000f6e18",
      "text": "> 2007年5月27日放送の作品No.5875「父さん発明の母([全自動卵割り機]が登場した回)」で、卵割り機を使って作った[だし巻き卵]を食べたフグ田マスオの「いやぁうまい！やっぱり機械で割った卵は、一味違いますよ〜！」というセリフが元ネタ。",
      "userId": "5d69dde930e3c500170f1ffd",
      "created": 1777618860,
      "updated": 1777618897
    },
    {
      "id": "69f44f8d00000000000f6e15",
      "text": "> ［……］",
      "userId": "5d69dde930e3c500170f1ffd",
      "created": 1777618829,
      "updated": 1777618834
    },
    {
      "id": "69f44f9300000000000f6e16",
      "text": "> だがセリフ自体の響きもさる事ながら、回自体の何処かカオスな雰囲気もあって非常に強いインパクトを残すセリフとなった。",
      "userId": "5d69dde930e3c500170f1ffd",
      "created": 1777618835,
      "updated": 1777618837
    },
    {
      "id": "69f44f9700000000000f6e17",
      "text": "[via. https://dic.pixiv.net/a/%E3%81%B3%E3%82%83%E3%81%82%E3%82%9B%E3%81%81%E3%82%9B%E3%82%9B%E3%81%81%E3%81%86%E3%81%BE%E3%81%B2%E3%81%83%E3%82%9B%E3%81%83%E3%81%83%E3%82%9B]",
      "userId": "5d69dde930e3c500170f1ffd",
      "created": 1777618839,
      "updated": 1777618844
    },
    {
      "id": "69f44f7c00000000000f6e14",
      "text": "",
      "userId": "5d69dde930e3c500170f1ffd",
      "created": 1777618812,
      "updated": 1777618812
    },
    {
      "id": "69f44f7a00000000000f6e12",
      "text": "[/arpla/びゃあ゛ぁ゛゛ぁうまひぃ゛ぃぃ゛ぃ゛]",
      "userId": "5d69dde930e3c500170f1ffd",
      "created": 1777618811,
      "updated": 1777618811
    },
    {
      "id": "69f44f7a00000000000f6e13",
      "text": "",
      "userId": "5d69dde930e3c500170f1ffd",
      "created": 1777618811,
      "updated": 1777618811
    }
  ]
}